latex_table_generator/__init__.py
latex_table_generator/generator.py
mylatexlib_itmo_367-1.0.2.dist-info/METADATA
mylatexlib_itmo_367-1.0.2.dist-info/WHEEL
mylatexlib_itmo_367-1.0.2.dist-info/top_level.txt
mylatexlib_itmo_367-1.0.2.dist-info/RECORD
