Metadata-Version: 2.1
Name: mylatexlib-itmo-367
Version: 1.0.2
Summary: A library for generating LaTeX tables and images.
Home-page: https://github.com/yourusername/mylatexlib
Author: Your Name
Author-email: your.email@example.com
License: MIT
Classifier: Programming Language :: Python :: 3
Classifier: License :: OSI Approved :: MIT License
Classifier: Operating System :: OS Independent
Requires-Python: >=3.6
